cloud189/__init__.py
cloud189/auth.py
cloud189/client.py
cloud189/constants.py
cloud189/store.py
cloud189/utils.py
cloud189-0.1.6.dist-info/licenses/LICENSE
cloud189-0.1.6.dist-info/METADATA
cloud189-0.1.6.dist-info/WHEEL
cloud189-0.1.6.dist-info/top_level.txt
cloud189-0.1.6.dist-info/RECORD
