Metadata-Version: 2.4
Name: cloud189
Version: 0.1.6
Summary: A Python SDK for interacting with Cloud189
Home-page: https://github.com/s0urcelab/cloud189
Author: s0urce
Author-email: me@src.moe
Classifier: Programming Language :: Python :: 3
Classifier: License :: OSI Approved :: MIT License
Classifier: Operating System :: OS Independent
Requires-Python: >=3.9
License-File: LICENSE
Requires-Dist: pycryptodome>=3.15.0
Requires-Dist: httpx==0.28.1
Dynamic: author
Dynamic: author-email
Dynamic: classifier
Dynamic: description
Dynamic: description-content-type
Dynamic: home-page
Dynamic: license-file
Dynamic: requires-dist
Dynamic: requires-python
Dynamic: summary
